setup.py
weatherca
data_gc_ca_api/__init__.py
data_gc_ca_api/__version__.py
data_gc_ca_api/cityweather.py
data_gc_ca_api.egg-info/PKG-INFO
data_gc_ca_api.egg-info/SOURCES.txt
data_gc_ca_api.egg-info/dependency_links.txt
data_gc_ca_api.egg-info/requires.txt
data_gc_ca_api.egg-info/top_level.txt