Metadata-Version: 1.0
Name: data-gc-ca-api
Version: 0.2.3
Summary: Utility for Accessing Environment Canada Data
Home-page: https://github.com/igable/data-gc-ca-api
Author: Ian Gable
Author-email: ian@gable.ca
License: 'GPL3' or 'Apache 2'
Platform: UNKNOWN
Classifier: Development Status :: 3 - Alpha
Classifier: Environment :: Console
Classifier: Intended Audience :: Developers
Classifier: Intended Audience :: End Users/Desktop
Classifier: Intended Audience :: Science/Research
Classifier: License :: OSI Approved :: Apache Software License
Classifier: License :: OSI Approved :: GNU General Public License (GPL)
Classifier: Operating System :: POSIX
Classifier: Programming Language :: Python
